{
    "type": "CARD",
    "categoryUrl": "https://courses.naomifisher.co.uk",
    "categoryPosition": 24,
    "title": "After School: Helping Your Autistic Child Move On from School Trauma",
    "imageURL": "https://kajabi-storefronts-production.kajabi-cdn.com/kajabi-storefronts-production/file-uploads/site/2147601926/images/370fd3b-0a3-35fc-33-8db2c25bf810_after-school-moving-on-from-school-trauma.webp",
    "description": "In this mini course Naomi will talk about school trauma, how it occurs, what makes it worse and how parents can help. You'll leave with a new understanding of what has gone on for your child, why they are still affected by the past, and some ideas of what to do. This course will combine psychological theory with practical strategies and ideas.",
    "price": "£40.00 GBP",
    "checkoutUrl": "https://courses.naomifisher.co.uk/offers/xvn8Y7TJ",
    "imageFileName": "after-school-helping-your-autistic-child-move-on-from-school-trauma.webp"
}