{
    "type": "CARD",
    "categoryUrl": "https://courses.naomifisher.co.uk",
    "categoryPosition": 23,
    "title": "What is Demand Avoidance? A Guide for Teenagers",
    "imageURL": "https://kajabi-storefronts-production.kajabi-cdn.com/kajabi-storefronts-production/file-uploads/site/2147601926/images/ac1b0e-fe2b-ef21-bb27-673737b2411f_what-is-demand-avoidance-a-guide-for-teenagers.png",
    "description": "In this course for teenagers, Naomi discusses the times when everything feels like pressure and your nervous system and how it works. She describes the pressure trap - how we can sometimes get into a trap when we feel under pressure - and how we can do things to help by building the world that works for you and by befriending your nervous system.\nWith short videos featuring Chloe from Me Just Me.",
    "price": "£40.00 GBP",
    "checkoutUrl": "https://courses.naomifisher.co.uk/offers/36wrrznS",
    "imageFileName": "what-is-demand-avoidance-a-guide-for-teenagers.png"
}