{
    "type": "CARD",
    "categoryUrl": "https://courses.naomifisher.co.uk/low-demand-parenting",
    "categoryPosition": 9,
    "title": "The Art of Low Demand Parenting: Screens",
    "imageURL": "https://kajabi-storefronts-production.kajabi-cdn.com/kajabi-storefronts-production/file-uploads/site/2147601926/images/b84d2fc-b0b6-8c37-20a4-752aff2a46_ALDP-7.png",
    "description": "How do you manage screen time, when your child doesn't play by the parenting rules?",
    "price": "£30.00 GBP",
    "checkoutUrl": "https://courses.naomifisher.co.uk/offers/4pkAj9xC",
    "imageFileName": "the-art-of-low-demand-parenting-screens.png"
}